apapi/__init__.py
apapi/__main__.py
apapi/__version__.py
apapi/alm.py
apapi/audit.py
apapi/authentication.py
apapi/basic_connection.py
apapi/bulk.py
apapi/connection.py
apapi/transactional.py
apapi/utils.py
apapi-0.6.0.dist-info/LICENSE
apapi-0.6.0.dist-info/METADATA
apapi-0.6.0.dist-info/WHEEL
apapi-0.6.0.dist-info/entry_points.txt
apapi-0.6.0.dist-info/top_level.txt
apapi-0.6.0.dist-info/RECORD
