Metadata-Version: 2.1
Name: apapi
Version: 0.6.0
Summary: Unofficial Anaplan API Python client library
Home-page: https://github.com/DLZaan/apapi
Author: Milosz Kierepka
Author-email: milosz.kierepka+work@gmail.com
Maintainer: Milosz Kierepka
Maintainer-email: milosz.kierepka+work@gmail.com
License: Apache 2.0
Project-URL: Documentation, https://dlzaan.github.io/apapi/apapi.html
Project-URL: Source, https://github.com/DLZaan/apapi
Project-URL: Changelog, https://github.com/DLZaan/apapi/releases
Keywords: anaplan anaplanapi anaplanconnector anaplanlibrary client
Platform: any
Classifier: Development Status :: 4 - Beta
Classifier: Intended Audience :: Developers
Classifier: License :: OSI Approved :: Apache Software License
Classifier: Natural Language :: English
Classifier: Operating System :: OS Independent
Classifier: Programming Language :: Python
Classifier: Programming Language :: Python :: 3
Classifier: Programming Language :: Python :: 3 :: Only
Classifier: Programming Language :: Python :: 3.8
Classifier: Programming Language :: Python :: 3.9
Classifier: Programming Language :: Python :: 3.10
Classifier: Programming Language :: Python :: 3.11
Classifier: Programming Language :: Python :: 3.12
Classifier: Topic :: Office/Business :: Financial
Classifier: Topic :: Software Development :: Libraries
Requires-Python: ~=3.8
License-File: LICENSE
Requires-Dist: requests~=2.28
Provides-Extra: dev
Requires-Dist: black~=25.0; extra == "dev"
Requires-Dist: isort~=5.13; extra == "dev"
Requires-Dist: pdoc~=15.0; extra == "dev"
Requires-Dist: twine~=4.0; extra == "dev"
Requires-Dist: wheel~=0.45; extra == "dev"
